README.md
setup.py
pycalculation.egg-info/PKG-INFO
pycalculation.egg-info/SOURCES.txt
pycalculation.egg-info/dependency_links.txt
pycalculation.egg-info/top_level.txt
pyclc/__init__.py
pyclc/__main__.py
pyclc/astrology.py
pyclc/general.py
pyclc/geometry.py
pyclc/maths.py
pyclc/physics.py